pathed/__init__.py
pathed-1.2.1.dist-info/LICENSE
pathed-1.2.1.dist-info/METADATA
pathed-1.2.1.dist-info/WHEEL
pathed-1.2.1.dist-info/top_level.txt
pathed-1.2.1.dist-info/RECORD
