Metadata-Version: 2.1
Name: pathed
Version: 1.2.1
Summary: Common Path and Importing Operations
Home-page: https://pypi.org/project/pathed/
Author: Jv Kyle Eclarin
Author-email: <jvykleeclarin@gmail.com>
License: UNKNOWN
Project-URL: Documentation, https://pypi.org/project/pathed/
Project-URL: Code, https://github.com/mathemusician/pathed
Project-URL: Issue tracker, https://github.com/mathemusician/pathed/issues
Keywords: python,pathing,path,pathed
Platform: UNKNOWN
Classifier: Development Status :: 3 - Alpha
Classifier: Intended Audience :: Education
Classifier: Programming Language :: Python :: 3.5
Classifier: Operating System :: MacOS :: MacOS X
Classifier: Operating System :: Microsoft :: Windows
Classifier: Operating System :: POSIX :: Linux
